dependance/__init__.py
dependance/post_install.py
utils_hex-1.0.0.dist-info/METADATA
utils_hex-1.0.0.dist-info/WHEEL
utils_hex-1.0.0.dist-info/top_level.txt
utils_hex-1.0.0.dist-info/RECORD
