Metadata-Version: 2.1
Name: utils_hex
Version: 1.0.0
Summary: Un exemple de package pour installer les hexs .
Author: Harmless
